{
  "220hz-saturated-sine-playback-rate-75.mp3": {
    "text": [
      "Copyright 2019 University of Colorado Boulder"
    ],
    "projectURL": "http://phet.colorado.edu",
    "license": "contact phethelp@colorado.edu",
    "notes": "created by Ashton Morris"
  },
  "ethereal-flute-for-meter-loop.mp3": {
    "text": [
      "Copyright 2019 University of Colorado Boulder"
    ],
    "projectURL": "http://phet.colorado.edu",
    "license": "contact phethelp@colorado.edu",
    "notes": "created by Ashton Morris"
  },
  "light-beam-loop-v5-eq-out-bass.mp3": {
    "text": [
      "Copyright 2019 University of Colorado Boulder"
    ],
    "projectURL": "http://phet.colorado.edu",
    "license": "contact phethelp@colorado.edu",
    "notes": "created by Ashton Morris"
  },
  "speaker-pulse-v4.mp3": {
    "text": [
      "Copyright 2019 University of Colorado Boulder"
    ],
    "projectURL": "http://phet.colorado.edu",
    "license": "contact phethelp@colorado.edu",
    "notes": "created by Ashton Morris"
  },
  "squishier-button-v3-007.mp3": {
    "text": [
      "Copyright 2020 University of Colorado Boulder"
    ],
    "projectURL": "http://phet.colorado.edu",
    "license": "contact phethelp@colorado.edu",
    "notes": "created by Ashton Morris"
  },
  "water-drop-v5.mp3": {
    "text": [
      "Copyright 2019 University of Colorado Boulder"
    ],
    "projectURL": "http://phet.colorado.edu",
    "license": "contact phethelp@colorado.edu",
    "notes": "created by Ashton Morris"
  },
  "water-drop-v5-001.mp3": {
    "text": [
      "Copyright 2019 University of Colorado Boulder"
    ],
    "projectURL": "http://phet.colorado.edu",
    "license": "contact phethelp@colorado.edu",
    "notes": "created by Ashton Morris"
  },
  "water-drop-v5-002.mp3": {
    "text": [
      "Copyright 2019 University of Colorado Boulder"
    ],
    "projectURL": "http://phet.colorado.edu",
    "license": "contact phethelp@colorado.edu",
    "notes": "created by Ashton Morris"
  },
  "water-drop-v5-003.mp3": {
    "text": [
      "Copyright 2019 University of Colorado Boulder"
    ],
    "projectURL": "http://phet.colorado.edu",
    "license": "contact phethelp@colorado.edu",
    "notes": "created by Ashton Morris"
  },
  "organ-for-meter-loop.mp3": {
    "text": [
      "Copyright 2019 University of Colorado Boulder"
    ],
    "projectURL": "http://phet.colorado.edu",
    "license": "contact phethelp@colorado.edu",
    "notes": "created by Ashton Morris"
  },
  "organ-v2-for-meter-loop.mp3": {
    "text": [
      "Copyright 2019 University of Colorado Boulder"
    ],
    "projectURL": "http://phet.colorado.edu",
    "license": "contact phethelp@colorado.edu",
    "notes": "created by Ashton Morris"
  },
  "slider-click-v2-left.mp3": {
    "text": [
      "Copyright 2020 University of Colorado Boulder"
    ],
    "projectURL": "http://phet.colorado.edu",
    "license": "contact phethelp@colorado.edu",
    "notes": "created by Ashton Morris"
  },
  "slider-clicks-idea-c-lower-end-click.mp3": {
    "text": [
      "Copyright 2020 University of Colorado Boulder"
    ],
    "projectURL": "http://phet.colorado.edu",
    "license": "contact phethelp@colorado.edu",
    "notes": "created by Ashton Morris"
  },
  "slider-clicks-idea-c-example.mp3": {
    "text": [
      "Copyright 2020 University of Colorado Boulder"
    ],
    "projectURL": "http://phet.colorado.edu",
    "license": "contact phethelp@colorado.edu",
    "notes": "created by Ashton Morris"
  },
  "slider-clicks-idea-c-example-left.mp3": {
    "text": [
      "Copyright 2020 University of Colorado Boulder"
    ],
    "projectURL": "http://phet.colorado.edu",
    "license": "contact phethelp@colorado.edu",
    "notes": "created by Ashton Morris"
  },
  "slider-click-v2-right.mp3": {
    "text": [
      "Copyright 2020 University of Colorado Boulder"
    ],
    "projectURL": "http://phet.colorado.edu",
    "license": "contact phethelp@colorado.edu",
    "notes": "created by Ashton Morris"
  },
  "windy-tone-for-meter-loop-rate-75-pitch-matched-fixed-less-high-end.mp3": {
    "text": [
      "Copyright 2020 University of Colorado Boulder"
    ],
    "projectURL": "http://phet.colorado.edu",
    "license": "contact phethelp@colorado.edu",
    "notes": "Adapted from MidiJS Soundfonts FatBoy harpsichord"
  }
}















